observable_collections-0.1.2.dist-info/METADATA
observable_collections-0.1.2.dist-info/RECORD
observable_collections-0.1.2.dist-info/WHEEL
observable_collections-0.1.2.dist-info/top_level.txt
reactive/CollectionChange.py
reactive/CollectionChangeAction.py
reactive/ObservableDict.py
reactive/ObservableList.py
reactive/ObservableSet.py
reactive/__init__.py
reactive/shared/AbstractObservableCollection.py
reactive/shared/CollectionChange.py
reactive/shared/CollectionChangeAction.py
reactive/shared/__init__.py
test/__init__.py
test/ObservableDict/__init__.py
test/ObservableDict/construction_test.py
test/ObservableDict/mutation_test.py
test/ObservableDict/rx_notification_test.py
test/ObservableList/__init__.py
test/ObservableList/concurrent_modification_test.py
test/ObservableList/construction_test.py
test/ObservableList/mutation_test.py
test/ObservableList/rx_notification_test.py
test/ObservableSet/__init__.py
test/ObservableSet/construction_test.py
test/ObservableSet/mutation_test.py
test/ObservableSet/rx_notification_test.py
