Metadata-Version: 2.1
Name: observable-collections
Version: 0.1.2
Summary: Rx based collections that supports change notification
Home-page: UNKNOWN
Author: Shiyam S
Author-email: austin.shyam@gmail.com
License: MIT
Download-URL: https://github.com/shyam-s00/ObservableCollections
Platform: UNKNOWN
Classifier: Programming Language :: Python :: 3.5
Classifier: License :: OSI Approved :: MIT License
Classifier: Development Status :: 3 - Alpha
Requires-Dist: rx
